typemallow2/__init__.py
typemallow2/mappings.py
typemallow2-0.0.3.dist-info/LICENSE
typemallow2-0.0.3.dist-info/METADATA
typemallow2-0.0.3.dist-info/WHEEL
typemallow2-0.0.3.dist-info/top_level.txt
typemallow2-0.0.3.dist-info/RECORD
