Metadata-Version: 2.1
Name: typemallow2
Version: 0.0.3
Summary: An elegant and automatic solution for generating/outputting Typescript interfaces and enums from your Marshmallow Schemas and enums classes.Extension of Aden Harold works on typemallow.
Home-page: https://github.com/adenh93/typemallow
Author: Jules Aubier
Author-email: jules.aubier97@gmail.com
License: UNKNOWN
Keywords: Marshmallow,Typescript,Python,Flask,Django
Platform: any
Requires-Dist: marshmallow (>=2.0.0)
Requires-Dist: marshmallow-enum (>=1.5)
